nomad_camels_driver_swabianinstruments_timetagger/__init__.py
nomad_camels_driver_swabianinstruments_timetagger/swabianinstruments_timetagger.py
nomad_camels_driver_swabianinstruments_timetagger/swabianinstruments_timetagger_ophyd.py
nomad_camels_driver_swabianinstruments_timetagger-0.1.2.dist-info/licenses/LICENSE.txt
nomad_camels_driver_swabianinstruments_timetagger-0.1.2.dist-info/METADATA
nomad_camels_driver_swabianinstruments_timetagger-0.1.2.dist-info/WHEEL
nomad_camels_driver_swabianinstruments_timetagger-0.1.2.dist-info/top_level.txt
nomad_camels_driver_swabianinstruments_timetagger-0.1.2.dist-info/RECORD
